protollm_api/__init__.py
protollm_api/backend/__init__.py
protollm_api/backend/bll/__init__.py
protollm_api/backend/bll/services/__init__.py
protollm_api/backend/bll/services/async_chat_complition.py
protollm_api/backend/bll/services/base.py
protollm_api/backend/bll/services/chat_complition.py
protollm_api/backend/broker.py
protollm_api/backend/config.py
protollm_api/backend/endpoints/__init__.py
protollm_api/backend/endpoints/async_chat.py
protollm_api/backend/endpoints/manage.py
protollm_api/backend/endpoints/sync_chat.py
protollm_api/backend/example.py
protollm_api/backend/exeption.py
protollm_api/backend/models/__init__.py
protollm_api/backend/models/job_context_models.py
protollm_api/object_interface/__init__.py
protollm_api/object_interface/message_queue/__init__.py
protollm_api/object_interface/message_queue/base.py
protollm_api/object_interface/message_queue/rabbitmq_adapter.py
protollm_api/object_interface/result_storage/__init__.py
protollm_api/object_interface/result_storage/base.py
protollm_api/object_interface/result_storage/models.py
protollm_api/object_interface/result_storage/redis_storage.py
protollm_api/utils/__init__.py
protollm_api/utils/utils.py
protollm_api/worker/__init__.py
protollm_api/worker/config.py
protollm_api/worker/example.py
protollm_api/worker/models/__init__.py
protollm_api/worker/models/base.py
protollm_api/worker/models/cpp_models.py
protollm_api/worker/models/fake_models.py
protollm_api/worker/models/hf_models.py
protollm_api/worker/models/open_api_llm.py
protollm_api/worker/models/README.md
protollm_api/worker/models/vllm_models.py
protollm_api/worker/services/__init__.py
protollm_api/worker/services/broker.py
protollm_api-1.1.5.dist-info/LICENSE
protollm_api-1.1.5.dist-info/METADATA
protollm_api-1.1.5.dist-info/WHEEL
protollm_api-1.1.5.dist-info/RECORD
