Metadata-Version: 2.3
Name: protollm-api
Version: 1.1.5
Summary: 
Author: aimclub
Requires-Python: >=3.10,<3.13
Classifier: Programming Language :: Python :: 3
Classifier: Programming Language :: Python :: 3.10
Classifier: Programming Language :: Python :: 3.11
Classifier: Programming Language :: Python :: 3.12
Requires-Dist: aioredis (>=2.0.1,<3.0.0)
Requires-Dist: fastapi (>=0.115.13,<0.116.0)
Requires-Dist: flower (==2.0.1)
Requires-Dist: llama-cpp-python[llama-cpp] (>=0.3.3,<0.4.0)
Requires-Dist: openai[openai] (>=1.88.0,<2.0.0)
Requires-Dist: pika (>=1.3.2,<2.0.0)
Requires-Dist: pydantic (>=2.7.4,<3.0.0)
Requires-Dist: redis (>=5.0.5,<6.0.0)
Requires-Dist: vllm[vllm] (>=0.7.2,<0.8.0)
